{
  "slideIndex": 23,
  "file": "04-2-xml-boundaries.html",
  "title": "입력 경계가 선명하면 모델의 오독이 줄어듭니다",
  "response": {
    "answer": "프롬프트 창에 코드, 요구사항, 참고할 문서까지 한꺼번에 길게 복사해서 붙여넣어 본 적, 다들 있으시죠? 분명 꼼꼼하게 지시를 적었는데, AI가 엉뚱하게 지시사항 텍스트 자체를 고쳐버리거나, 방대한 참고 자료에 파묻혀서 정작 가장 중요한 요청은 까먹는 답답한 경우를 종종 겪습니다.\n\n이런 일이 벌어지는 건 AI의 지능 문제가 아닙니다. 사람으로 치면, 작업대 위에 작업 지시서와 참고용 도면, 그리고 결과물을 적어 낼 빈 양식을 몽땅 뒤섞어서 던져준 것과 같습니다. AI도 이렇게 텍스트가 섞여 있으면 무엇이 자기가 지켜야 할 규칙이고 무엇이 그냥 참고할 데이터인지 구분하느라 에너지를 낭비하고, 결국 오독을 하게 됩니다.\n\n그래서 요청이 길어질 때는 작업대 위에 서류함을 명확히 나누듯, 물리적인 경계를 확실히 그어주어야 합니다. 괄호 모양의 XML 태그를 쓰거나 대문자 섹션 제목을 달아서 각 텍스트의 역할을 선명하게 분리해 주는 겁니다.\n\n구체적으로 작업대 위 공간은 크게 세 구역으로 나누시길 권장합니다. 첫째, AI가 당장 행동으로 옮겨야 할 '지시'와 단순히 읽기만 할 '참고 자료'를 철저히 분리하세요. 둘째, 결과물을 표로 줄지 목록으로 줄지 지정하는 '출력 형식'은 눈에 띄게 별도의 블록으로 빼두는 것이 좋습니다. 셋째, 실무에서 가장 흔히 하는 실수인데요. 우리가 고치고 싶은 '코드' 본문과 이렇게 고쳐달라는 '요구사항'이 절대 한 문단 안에 섞이지 않게 경계를 쳐주셔야 합니다.\n\n이렇게 입력 경계를 선명하게 나눠주면, 모델이 자의적으로 빈칸을 추측할 여지가 크게 줄어듭니다. 나중에 결과물이 제대로 나왔는지 검증할 때도, 어떤 서류함을 기준으로 대조해 봐야 할지 기준이 뚜렷해지죠. AI가 흔들리지 않고 일관되게 일할 수 있는 작업 환경은 바로 이 선명한 구역 나누기에서 시작됩니다.\n\n자, 이렇게 작업대 위에 어떤 정보를 어디에 둘지 구역을 깔끔하게 나눴다면, 이제 이 정보들을 바탕으로 일할 '작업자'를 부를 차례입니다. 우리는 흔히 AI에게 \"시니어 개발자처럼 행동해\"라고 역할을 주곤 하는데요. 이런 막연한 이름표를 붙여주는 것과 명확한 판단 기준을 쥐여주는 것은 과연 실제 작업에서 어떤 차이를 만들까요?",
    "conversation_id": "04f32e47-b19b-45ea-897e-20805af6d1b4",
    "turn_number": 1,
    "is_follow_up": false,
    "references": []
  }
}
